{
    "type_d_how_1": "d",
    "type_d_how_2": "b",
    "type_d_how_3": "c",
    "type_d_how_4": "d",
    "type_d_how_5": "e",
    "type_d_how_6": "b",
    "type_d_how_7": "c",
    "type_d_how_8": "d",
    "type_d_how_9": "d",
    "type_d_how_10": "b",
    "type_d_how_11": "e",
    "type_d_how_12": "b",
    "type_d_how_13": "e",
    "type_d_how_14": "b",
    "type_d_how_15": "c",
    "type_d_how_16": "b",
    "type_d_why_1": "l",
    "type_d_why_2": "n",
    "type_d_why_3": "l",
    "type_d_why_4": "m",
    "type_d_why_5": "i",
    "type_d_why_6": "j",
    "type_d_why_7": "k",
    "type_d_why_8": "m",
    "type_d_why_9": "i",
    "type_d_why_10": "j",
    "type_d_why_11": "l",
    "type_d_why_12": "m",
    "type_d_why_13": "i",
    "type_d_why_14": "j",
    "type_d_why_15": "l",
    "type_d_why_16": "m",
    "type_d_whether_1": "c",
    "type_d_whether_2": "d",
    "type_d_whether_3": "c",
    "type_d_whether_4": "d",
    "type_d_whether_5": "b",
    "type_d_whether_6": "b",
    "type_d_whether_7": "c",
    "type_d_whether_8": "d",
    "type_d_whether_9": "d",
    "type_d_whether_10": "b",
    "type_d_whether_11": "e",
    "type_d_whether_12": "b",
    "type_d_whether_13": "e",
    "type_d_whether_14": "b",
    "type_d_whether_15": "c",
    "type_d_whether_16": "b",
    "type_c_how_1": "d",
    "type_c_how_2": "a",
    "type_c_how_3": "b",
    "type_c_how_4": "d",
    "type_c_how_5": "g",
    "type_c_how_6": "d",
    "type_c_how_7": "a",
    "type_c_how_8": "b",
    "type_c_how_9": "d",
    "type_c_how_10": "d",
    "type_c_how_11": "d",
    "type_c_how_12": "d",
    "type_c_how_13": "b",
    "type_c_how_14": "b",
    "type_c_how_15": "d",
    "type_c_how_16": "b",
    "type_c_how_17": "b",
    "type_c_how_18": "e",
    "type_c_how_19": "c",
    "type_c_how_20": "a",
    "type_a_what_1": "e",
    "type_a_what_2": "g",
    "type_a_what_3": "b",
    "type_a_what_4": "h",
    "type_a_what_5": "a",
    "type_a_what_6": "e",
    "type_a_what_7": "a",
    "type_a_what_8": "b",
    "type_a_what_9": "h",
    "type_a_what_10": "a",
    "type_a_what_11": "d",
    "type_a_what_12": "g",
    "type_a_what_13": "g",
    "type_a_what_14": "h",
    "type_a_what_15": "a",
    "type_a_what_16": "a",
    "type_a_what_17": "b",
    "type_a_what_18": "g",
    "type_a_what_19": "b",
    "type_a_what_20": "a",
    "accuracy": 0.19718309859154928,
    "question_count": 71,
    "error_list": [
        {
            "id": "type_d_how_1",
            "answer": "d",
            "truth": "e",
            "wrong_reason": "type_d_how_time_order"
        },
        {
            "id": "type_d_how_3",
            "answer": "c",
            "truth": "b",
            "wrong_reason": "type_d_how_time_order"
        },
        {
            "id": "type_d_how_4",
            "answer": "d",
            "truth": "g",
            "wrong_reason": "type_d_how_recognize_time_stage_completeness"
        },
        {
            "id": "type_d_why_1",
            "answer": "l",
            "truth": "i",
            "wrong_reason": "type_d_why_recognize_belief_emotion_intention_action"
        },
        {
            "id": "type_d_why_2",
            "answer": "n",
            "truth": "m",
            "wrong_reason": "type_d_why_recognize_belief_emotion_intention_action"
        },
        {
            "id": "type_d_why_3",
            "answer": "l",
            "truth": "f",
            "wrong_reason": "type_d_why_recognize_belief_emotion_intention_action"
        },
        {
            "id": "type_d_why_4",
            "answer": "m",
            "truth": "f",
            "wrong_reason": "type_d_why_recognize_belief_emotion_intention_action"
        },
        {
            "id": "type_d_why_5",
            "answer": "i",
            "truth": "a",
            "wrong_reason": "type_d_why_recognize_belief_emotion_intention_action"
        },
        {
            "id": "type_d_why_6",
            "answer": "j",
            "truth": "b",
            "wrong_reason": "type_d_why_recognize_belief_emotion_intention_action"
        },
        {
            "id": "type_d_why_7",
            "answer": "k",
            "truth": "j",
            "wrong_reason": "type_d_why_recognize_belief_emotion_intention_action"
        },
        {
            "id": "type_d_why_8",
            "answer": "m",
            "truth": "c",
            "wrong_reason": "type_d_why_recognize_belief_emotion_intention_action"
        },
        {
            "id": "type_d_why_9",
            "answer": "i",
            "truth": "l",
            "wrong_reason": "type_d_why_recognize_belief_emotion_intention_action"
        },
        {
            "id": "type_d_why_10",
            "answer": "j",
            "truth": "d",
            "wrong_reason": "type_d_why_recognize_belief_emotion_intention_action"
        },
        {
            "id": "type_d_why_11",
            "answer": "l",
            "truth": "k",
            "wrong_reason": "type_d_why_recognize_belief_emotion_intention_action"
        },
        {
            "id": "type_d_why_12",
            "answer": "m",
            "truth": "p",
            "wrong_reason": "type_d_why_time_stage"
        },
        {
            "id": "type_d_why_13",
            "answer": "i",
            "truth": "f",
            "wrong_reason": "type_d_why_time_stage"
        },
        {
            "id": "type_d_why_14",
            "answer": "j",
            "truth": "k",
            "wrong_reason": "type_d_why_recognize_belief_emotion_intention_action"
        },
        {
            "id": "type_d_why_15",
            "answer": "l",
            "truth": "b",
            "wrong_reason": "type_d_why_recognize_belief_emotion_intention_action"
        },
        {
            "id": "type_d_why_16",
            "answer": "m",
            "truth": "i",
            "wrong_reason": "type_d_why_recognize_belief_emotion_intention_action"
        },
        {
            "id": "type_d_whether_1",
            "answer": "c",
            "truth": "d",
            "wrong_reason": "type_d_whether_time_stage"
        },
        {
            "id": "type_d_whether_5",
            "answer": "b",
            "truth": "a",
            "wrong_reason": "type_d_whether_time_stage"
        },
        {
            "id": "type_d_whether_6",
            "answer": "b",
            "truth": "e",
            "wrong_reason": "type_d_whether_time_stage"
        },
        {
            "id": "type_d_whether_7",
            "answer": "c",
            "truth": "b",
            "wrong_reason": "type_d_whether_recognize_if_change"
        },
        {
            "id": "type_d_whether_8",
            "answer": "d",
            "truth": "e",
            "wrong_reason": "type_d_whether_recognize_if_change"
        },
        {
            "id": "type_d_whether_10",
            "answer": "b",
            "truth": "d",
            "wrong_reason": "type_d_whether_time_stage"
        },
        {
            "id": "type_d_whether_11",
            "answer": "e",
            "truth": "d",
            "wrong_reason": "type_d_whether_recognize_if_change"
        },
        {
            "id": "type_d_whether_12",
            "answer": "b",
            "truth": "a",
            "wrong_reason": "type_d_whether_time_stage"
        },
        {
            "id": "type_d_whether_13",
            "answer": "e",
            "truth": "d",
            "wrong_reason": "type_d_whether_recognize_if_change"
        },
        {
            "id": "type_d_whether_15",
            "answer": "c",
            "truth": "d",
            "wrong_reason": "type_d_whether_time_stage"
        },
        {
            "id": "type_d_whether_16",
            "answer": "b",
            "truth": "d",
            "wrong_reason": "type_d_whether_time_stage"
        },
        {
            "id": "type_c_how_1",
            "answer": "d",
            "truth": "b",
            "wrong_reason": "type_c_how_time_stage"
        },
        {
            "id": "type_c_how_2",
            "answer": "a",
            "truth": "c",
            "wrong_reason": "type_c_how_recognizae_influence_between_not_belief_emotion"
        },
        {
            "id": "type_c_how_3",
            "answer": "b",
            "truth": "a",
            "wrong_reason": "type_c_how_recognizae_influence_between_not_belief_emotion"
        },
        {
            "id": "type_c_how_5",
            "answer": "g",
            "truth": "a",
            "wrong_reason": "type_c_how_recognizae_influence_between_not_belief_emotion"
        },
        {
            "id": "type_c_how_8",
            "answer": "b",
            "truth": "e",
            "wrong_reason": "type_c_how_time_stage"
        },
        {
            "id": "type_c_how_9",
            "answer": "d",
            "truth": "b",
            "wrong_reason": "type_c_how_time_stage"
        },
        {
            "id": "type_c_how_12",
            "answer": "d",
            "truth": "e",
            "wrong_reason": "type_c_how_recognizae_influence_between_not_belief_emotion"
        },
        {
            "id": "type_c_how_13",
            "answer": "b",
            "truth": "c",
            "wrong_reason": "type_c_how_time_stage"
        },
        {
            "id": "type_c_how_14",
            "answer": "b",
            "truth": "d",
            "wrong_reason": "type_c_how_recognizae_influence_between_not_belief_emotion"
        },
        {
            "id": "type_c_how_15",
            "answer": "d",
            "truth": "b",
            "wrong_reason": "type_c_how_recognizae_influence_between_not_belief_emotion"
        },
        {
            "id": "type_a_what_1",
            "answer": "e",
            "truth": "a",
            "wrong_reason": "type_a_what_recognize_belief_emotion_intention_action"
        },
        {
            "id": "type_a_what_2",
            "answer": "g",
            "truth": "a",
            "wrong_reason": "type_a_what_time_stage"
        },
        {
            "id": "type_a_what_3",
            "answer": "b",
            "truth": "g",
            "wrong_reason": "type_a_what_time_stage"
        },
        {
            "id": "type_a_what_4",
            "answer": "h",
            "truth": "a",
            "wrong_reason": "type_a_what_time_stage"
        },
        {
            "id": "type_a_what_6",
            "answer": "e",
            "truth": "f",
            "wrong_reason": "type_a_what_time_stage"
        },
        {
            "id": "type_a_what_7",
            "answer": "a",
            "truth": "d",
            "wrong_reason": "type_a_what_recognize_belief_emotion_intention_action"
        },
        {
            "id": "type_a_what_8",
            "answer": "b",
            "truth": "a",
            "wrong_reason": "type_a_what_time_stage"
        },
        {
            "id": "type_a_what_9",
            "answer": "h",
            "truth": "f",
            "wrong_reason": "type_a_what_recognize_belief_emotion_intention_action"
        },
        {
            "id": "type_a_what_10",
            "answer": "a",
            "truth": "g",
            "wrong_reason": "type_a_what_time_stage"
        },
        {
            "id": "type_a_what_11",
            "answer": "d",
            "truth": "a",
            "wrong_reason": "type_a_what_time_stage"
        },
        {
            "id": "type_a_what_12",
            "answer": "g",
            "truth": "d",
            "wrong_reason": "type_a_what_recognize_belief_emotion_intention_action"
        },
        {
            "id": "type_a_what_14",
            "answer": "h",
            "truth": "e",
            "wrong_reason": "type_a_what_recognize_belief_emotion_intention_action"
        },
        {
            "id": "type_a_what_16",
            "answer": "a",
            "truth": "c",
            "wrong_reason": "type_a_what_time_stage"
        },
        {
            "id": "type_a_what_17",
            "answer": "b",
            "truth": "c",
            "wrong_reason": "type_a_what_time_stage"
        },
        {
            "id": "type_a_what_18",
            "answer": "g",
            "truth": "a",
            "wrong_reason": "type_a_what_recognize_belief_emotion_intention_action"
        },
        {
            "id": "type_a_what_19",
            "answer": "b",
            "truth": "f",
            "wrong_reason": "type_a_what_recognize_belief_emotion_intention_action"
        },
        {
            "id": "type_a_what_20",
            "answer": "a",
            "truth": "e",
            "wrong_reason": "type_a_what_recognize_belief_emotion_intention_action"
        }
    ],
    "error_analysis": {
        "type_d_how_time_order": 2,
        "type_d_how_recognize_time_stage_completeness": 1,
        "type_d_why_recognize_belief_emotion_intention_action": 14,
        "type_d_why_time_stage": 2,
        "type_d_whether_time_stage": 7,
        "type_d_whether_recognize_if_change": 4,
        "type_c_how_time_stage": 4,
        "type_c_how_recognizae_influence_between_not_belief_emotion": 6,
        "type_a_what_recognize_belief_emotion_intention_action": 8,
        "type_a_what_time_stage": 9,
        "total": 57
    }
}