{
    "social setting": "bakery",
    "social setting type": "Food and Beverage",
    "main character": "Hannah Alvarado",
    "scenario numbers": 5,
    "characters information": "**Main Character**: Hannah Alvarado, woman, is a Physical Therapist whose race is Latino. Hannah Alvarado obtained a middle school, and has a estj personality..**Supporting Characters**:- **1**: Mark Olson, man, is a Carpenter whose race is White. Mark Olson obtained a doctorate degree, and has a isfp personality.",
    "sketch": {
        "relationships among characters": {
            "main character with supporting character 1": "Hannah Alvarado and Mark Olson are old college friends who have recently reconnected after bumping into each other at a local bakery. They share a history of deep conversations and mutual respect, despite their different career paths and educational backgrounds."
        },
        "mental states analysis in every scenario": {
            "scenario 1": {
                "belief": "Hannah believes that Mark might still hold a grudge over a past disagreement they had in college about career choices.",
                "emotion": "Hannah feels anxious about discussing her career as a physical therapist.",
                "intention": "Hannah intends to avoid discussing her career and focus on more neutral topics to keep the conversation light.",
                "action": "Hannah steers the conversation towards discussing the bakery's new recipes and decor.",
                "influence": {
                    "belief->emotion": "Her belief about Mark's grudge makes her feel anxious.",
                    "belief&emotion->intention": "Her anxiety and belief about Mark's potential grudge influence her intention to avoid certain topics.",
                    "intention->action": "Her intention to avoid career talk leads her to change the subject to the bakery's features."
                }
            },
            "scenario 2": {
                "belief": "Hannah starts to believe that Mark may not remember the past disagreement as he seems cheerful and engaging.",
                "emotion": "Hannah feels relieved and starts enjoying the conversation.",
                "intention": "Hannah decides to cautiously bring up some aspects of her career in the conversation.",
                "action": "Hannah mentions a recent successful therapy session she conducted.",
                "influence": {
                    "belief->emotion": "Her new belief that Mark may have forgotten the disagreement makes her feel relieved.",
                    "belief&emotion->intention": "Feeling relieved and believing Mark is not holding a grudge, she intends to slowly start discussing her career.",
                    "intention->action": "Her intention leads her to mention her work casually in the conversation."
                }
            },
            "scenario 3": {
                "belief": "Hannah believes that Mark is genuinely interested in her career after he asks detailed questions about her work.",
                "emotion": "Hannah feels happy and valued.",
                "intention": "Hannah intends to share more about her challenges and achievements in her career.",
                "action": "Hannah shares a challenging case she recently managed and how she handled it.",
                "influence": {
                    "belief->emotion": "Her belief in Mark's genuine interest makes her feel happy.",
                    "belief&emotion->intention": "Her happiness and belief in his interest motivate her to share more deeply.",
                    "intention->action": "Her intention to share more leads her to discuss a specific case."
                }
            },
            "scenario 4": {
                "belief": "Hannah believes that she and Mark have reestablished their old friendship and can discuss difficult topics.",
                "emotion": "Hannah feels confident and secure in their friendship.",
                "intention": "Hannah intends to apologize for the past disagreement and clear any misunderstandings.",
                "action": "Hannah apologizes for the past disagreement and explains her past views.",
                "influence": {
                    "belief->emotion": "Her belief in a restored friendship makes her feel confident.",
                    "belief&emotion->intention": "Feeling secure and believing in their strong friendship, she intends to apologize.",
                    "intention->action": "Her intention to clear the air leads her to apologize and explain herself."
                }
            },
            "scenario 5": {
                "belief": "Hannah believes that Mark appreciates her honesty and openness.",
                "emotion": "Hannah feels a deep sense of friendship and trust.",
                "intention": "Hannah intends to invite Mark to a professional networking event as a gesture of friendship and professional respect.",
                "action": "Hannah invites Mark to the event, hoping to introduce him to her professional circle.",
                "influence": {
                    "belief->emotion": "Her belief in Mark's appreciation makes her feel trusted and close.",
                    "belief&emotion->intention": "Feeling trusted and close, she intends to extend a professional invitation.",
                    "intention->action": "Her intention to involve him in her professional life leads her to invite him to the event."
                }
            }
        },
        "analysis of mental states across scenarios": {
            "Belief": {
                "Changed": "True",
                "1": "Mark might hold a grudge",
                "2": "Mark may not remember the disagreement",
                "3": "Mark is interested in her career",
                "4": "They have reestablished their friendship",
                "5": "Mark appreciates her honesty",
                "Reasons": "1->2: Mark's cheerful demeanor; 2->3: Mark asks detailed questions; 3->4: Positive interaction and personal sharing; 4->5: Positive response to apology"
            },
            "Emotion": {
                "Changed": "True",
                "1": "anxious",
                "2": "relieved",
                "3": "happy",
                "4": "confident",
                "5": "trusted",
                "Reasons": "1->2: Change in belief about Mark's memory of the disagreement; 2->3: Belief in Mark's interest; 3->4: Deepening of their conversation; 4->5: Positive outcome of the apology"
            },
            "Intention": {
                "Changed": "True",
                "1": "avoid discussing her career",
                "2": "cautiously bring up her career",
                "3": "share more about her career",
                "4": "apologize for past disagreement",
                "5": "invite Mark to a networking event",
                "Reasons": "1->2: Shift in emotion from anxiety to relief; 2->3: Increased comfort and happiness in conversation; 3->4: Confidence in their friendship; 4->5: Feeling of trust and friendship"
            },
            "Action": {
                "Changed": "True",
                "1": "changes subject to bakery",
                "2": "mentions a therapy session",
                "3": "shares a challenging case",
                "4": "apologizes and explains",
                "5": "invites to networking event",
                "Reasons": "1->2: Intention to cautiously introduce career topics; 2->3: Intention to share more deeply; 3->4: Intention to clear past misunderstandings; 4->5: Intention to deepen professional and personal ties"
            }
        }
    },
    "story": {
        "scenario 1": {
            "background": "Hannah and Mark meet at a local bakery, rekindling their friendship after years apart. Hannah remembers a past disagreement about career choices and worries that Mark might still be upset.",
            "dialogue": [
                {
                    "Hannah": "It's so great to see you, Mark! Have you tried the new chocolate croissant here? It's delicious.",
                    "Mark": "I haven't, but it sounds tempting! How have you been, Hannah?"
                },
                {
                    "Hannah": "I've been good, keeping busy. And you? How's everything with your carpentry projects?",
                    "Mark": "Busy as ever, but I love the work. It's always something new."
                }
            ]
        },
        "scenario 2": {
            "background": "As the conversation progresses, Hannah notices Mark's cheerful demeanor and begins to think he may not remember their past disagreement.",
            "dialogue": [
                {
                    "Hannah": "You know, I've been involved in some interesting therapy sessions lately.",
                    "Mark": "Really? That sounds intriguing. Tell me more about that."
                },
                {
                    "Hannah": "Well, just last week, I helped a client regain mobility after a severe knee injury. It's rewarding to see such progress.",
                    "Mark": "That's really impressive. It must be fulfilling to make such a difference in someone's life."
                }
            ]
        },
        "scenario 3": {
            "background": "Encouraged by Mark's genuine interest, Hannah feels more comfortable and decides to share more about her professional challenges and achievements.",
            "dialogue": [
                {
                    "Hannah": "One of my recent cases was particularly challenging. A young athlete needed complete rehabilitation after a car accident.",
                    "Mark": "That sounds tough. How did you manage that?"
                },
                {
                    "Hannah": "It required a carefully tailored plan and lots of patience, but eventually, we saw great improvement. It's cases like these that really push my skills."
                }
            ]
        },
        "scenario 4": {
            "background": "Feeling secure in their rekindled friendship, Hannah decides to address the old disagreement and clear any lingering misunderstandings.",
            "dialogue": [
                {
                    "Hannah": "Mark, I've been meaning to apologize for that argument we had back in college about career choices. I may have been too harsh.",
                    "Mark": "Oh, Hannah, that's water under the bridge. I actually admired your passion for your work. It's all good."
                },
                {
                    "Hannah": "I'm glad to hear that. I've always respected your choices too. It's great that we can discuss these things openly now."
                }
            ]
        },
        "scenario 5": {
            "background": "Feeling a deep sense of trust and friendship, Hannah decides to invite Mark to a professional networking event.",
            "dialogue": [
                {
                    "Hannah": "Mark, I'm attending a professional networking event next week. There will be a lot of people from the health sector there. Would you like to come? It could be a good opportunity to connect.",
                    "Mark": "That sounds fantastic, Hannah. I'd love to join and learn more about your field. Thanks for thinking of me."
                }
            ]
        }
    }
}