{
    "social setting": "office",
    "social setting type": "Work and Office",
    "main character": "Julie Lai",
    "scenario numbers": 5,
    "characters information": "**Main Character**: Julie Lai, woman, is a Event Planner whose race is Native Hawaiian and Other Pacific Islander. Julie Lai obtained a doctorate degree, and has a enfj personality..**Supporting Characters**:- **1**: Gloria Bullbear, woman, is a Public Relations Specialist whose race is Alaska Native. Gloria Bullbear obtained a doctorate degree, and has a istj personality.",
    "sketch": {
        "relationships among characters": {
            "main character with supporting character 1": "Julie Lai and Gloria Bullbear are colleagues in a large corporate event planning company. They have a professional relationship that is cordial but occasionally strained due to differing work styles and communication methods. Julie, with her ENFJ personality, is more people-oriented and empathetic, while Gloria, with her ISTJ personality, is more detail-oriented and structured."
        },
        "mental states analysis in every scenario": {
            "scenario 1": {
                "belief": "Julie believes that Gloria's structured approach might be slowing down the project's progress.",
                "emotion": "Frustrated",
                "intention": "To suggest a more flexible approach in the meeting",
                "action": "Julie proposes a new, more adaptive strategy during a team meeting.",
                "influence": {
                    "belief->emotion": "Julie's belief that the project is being slowed down causes her frustration.",
                    "belief&emotion->intention": "Her frustration, combined with her belief, motivates her to change the approach.",
                    "intention->action": "Her intention to suggest changes directly leads to her action of proposing a new strategy."
                }
            },
            "scenario 2": {
                "belief": "Julie now believes that Gloria might feel undermined by her suggestions.",
                "emotion": "Concerned",
                "intention": "To reassure Gloria and seek her input",
                "action": "Julie approaches Gloria privately to discuss the project and express her appreciation for Gloria's efforts.",
                "influence": {
                    "belief->emotion": "Julie's belief that Gloria might feel undermined makes her feel concerned.",
                    "belief&emotion->intention": "Her concern and belief about Gloria's feelings motivate her to mend their relationship.",
                    "intention->action": "Her intention to reassure Gloria leads to the action of having a private conversation."
                }
            },
            "scenario 3": {
                "belief": "Julie believes that her approach has positively influenced the project's pace without hurting Gloria's feelings.",
                "emotion": "Relieved",
                "intention": "To continue the new strategy while keeping open communication with Gloria",
                "action": "Julie sends an email to the team outlining the next steps and openly credits Gloria for her contributions.",
                "influence": {
                    "belief->emotion": "Julie's belief in the positive outcome of her actions makes her feel relieved.",
                    "belief&emotion->intention": "Feeling relieved and believing in the efficacy of her approach, she decides to continue it.",
                    "intention->action": "Her intention to maintain the strategy and communication results in sending an appreciative email."
                }
            },
            "scenario 4": {
                "belief": "Julie believes that the project's success might lead to her promotion, but worries about Gloria's reaction.",
                "emotion": "Anxious",
                "intention": "To ensure Gloria feels valued and considered for her own advancement",
                "action": "Julie discusses potential career advancements with Gloria and suggests they both apply for upcoming positions.",
                "influence": {
                    "belief->emotion": "Julie's belief in potential promotion causes anxiety about Gloria's reaction.",
                    "belief&emotion->intention": "Her anxiety and belief about the promotion motivate her to ensure Gloria feels valued.",
                    "intention->action": "Her intention to discuss career advancements leads to the action of suggesting joint applications."
                }
            },
            "scenario 5": {
                "belief": "Julie believes that she and Gloria have developed a strong professional bond.",
                "emotion": "Happy",
                "intention": "To solidify their partnership and collaborate on more projects",
                "action": "Julie proposes a co-led initiative for a major upcoming event to the senior management.",
                "influence": {
                    "belief->emotion": "Julie's belief in their strengthened relationship makes her feel happy.",
                    "belief&emotion->intention": "Her happiness and belief in their effective collaboration motivate her to propose a joint initiative.",
                    "intention->action": "Her intention to collaborate more closely leads to the action of proposing a new project."
                }
            }
        },
        "analysis of mental states across scenarios": {
            "Belief": {
                "Changed": "True",
                "1": "Project slowing down",
                "2": "Gloria might feel undermined",
                "3": "Approach positively influenced the project",
                "4": "Project success might lead to promotion",
                "5": "Strong professional bond developed",
                "Reasons": "1->2: Julie's action and Gloria's reaction; 2->3: Outcome of their conversation; 3->4: Project outcomes and personal aspirations; 4->5: Outcome of their career discussion"
            },
            "Emotion": {
                "Changed": "True",
                "1": "Frustrated",
                "2": "Concerned",
                "3": "Relieved",
                "4": "Anxious",
                "5": "Happy",
                "Reasons": "1->2: Reaction to Gloria's perceived feelings; 2->3: Positive feedback from Gloria; 3->4: Concerns about personal and professional implications; 4->5: Positive developments in their relationship"
            },
            "Intention": {
                "Changed": "True",
                "1": "Suggest a more flexible approach",
                "2": "Reassure Gloria and seek her input",
                "3": "Continue the new strategy and keep open communication",
                "4": "Ensure Gloria feels valued and considered for advancement",
                "5": "Solidify partnership and collaborate on more projects",
                "Reasons": "1->2: Response to Gloria's reaction and Julie's own concerns; 2->3: Positive outcome of their interaction; 3->4: New opportunities and challenges; 4->5: Strengthened professional relationship"
            },
            "Action": {
                "Changed": "True",
                "1": "Proposes a new strategy",
                "2": "Approaches Gloria privately",
                "3": "Sends an appreciative email",
                "4": "Discusses career advancements",
                "5": "Proposes a co-led initiative",
                "Reasons": "1->2: Need to address interpersonal issues; 2->3: Desire to maintain positive momentum; 3->4: Preparing for potential opportunities; 4->5: Desire to further strengthen partnership"
            }
        }
    },
    "story": {
        "scenario 1": {
            "background": "During a team meeting at the corporate event planning company, Julie feels that the project's progress is being hindered by Gloria's overly structured approach.",
            "dialogue": [
                {
                    "Julie": "Gloria, I appreciate your attention to detail, but I believe we might need to adopt a more flexible strategy to meet our deadlines efficiently.",
                    "Gloria": "I understand your concern, Julie, but the structure is crucial to ensure we don't miss anything important. Can you suggest how we might be more flexible without risking oversight?"
                }
            ]
        },
        "scenario 2": {
            "background": "After the meeting, Julie senses that Gloria might feel undermined by her suggestions and decides to address it privately to maintain their professional relationship.",
            "dialogue": [
                {
                    "Julie": "Gloria, I wanted to thank you for your hard work and clarify that my earlier suggestions were aimed at enhancing our project, not undermining your methods.",
                    "Gloria": "Thank you, Julie. I appreciate you bringing this up. I do feel a bit sidelined, but I'm open to discussing how we can integrate more flexibility into our workflow."
                }
            ]
        },
        "scenario 3": {
            "background": "Following their private conversation, Julie believes that her approach has positively influenced the project's pace and Gloria's feelings. She decides to reinforce this in a team email.",
            "dialogue": [
                {
                    "Julie": "Team, I'd like to outline our next steps and also take a moment to credit Gloria for her invaluable contributions, which have been essential in our recent successes.",
                    "Gloria": "Thank you, Julie. I'm glad to see our collaboration is yielding results. I look forward to continuing this path."
                }
            ]
        },
        "scenario 4": {
            "background": "As the project nears completion, Julie contemplates the possibility of a promotion. However, she is anxious about how this might affect her relationship with Gloria and discusses potential career advancements with her.",
            "dialogue": [
                {
                    "Julie": "Gloria, I've been thinking about the future and how this project might open up new opportunities for us. Maybe we should consider applying for the upcoming positions together?",
                    "Gloria": "That sounds like a thoughtful idea, Julie. It's good to know we can look out for each other's growth in this company."
                }
            ]
        },
        "scenario 5": {
            "background": "Encouraged by their strengthened professional relationship, Julie proposes a co-led initiative for a major upcoming event to the senior management, aiming to solidify their partnership.",
            "dialogue": [
                {
                    "Julie": "I believe that Gloria and I have developed a strong partnership that can greatly benefit our future projects. I propose that we co-lead the upcoming major event.",
                    "Gloria": "I'm thrilled by this proposal, Julie. It's a testament to how far we've come as a team. Let's make it a success."
                }
            ]
        }
    }
}